./.gitignore
./PKG-INFO
./README.md
./pyproject.toml
./vision_agents/plugins/decart/__init__.py
./vision_agents/plugins/decart/decart_restyling_processor.py
./vision_agents/plugins/decart/decart_video_track.py
vision_agents_plugins_decart-0.2.10.dist-info/METADATA
vision_agents_plugins_decart-0.2.10.dist-info/WHEEL
vision_agents_plugins_decart-0.2.10.dist-info/RECORD
