Metadata-Version: 2.4
Name: vision-agents-plugins-decart
Version: 0.2.10
Summary: Decart plugin for Vision Agents
Project-URL: Documentation, https://visionagents.ai/
Project-URL: Website, https://visionagents.ai/
Project-URL: Source, https://github.com/GetStream/Vision-Agents
License-Expression: MIT
Keywords: AI,agents,decart,voice agents
Requires-Python: >=3.10
Requires-Dist: decart==0.0.8
Requires-Dist: vision-agents
